[
  {
    "rank": 1,
    "title": "正しく評価される自己評価の書き方 - るさんちまん",
    "url": "https://naopr.hatenablog.com/entry/2024/09/22/093117",
    "hatena_url": "https://b.hatena.ne.jp/entry?url=https%3A%2F%2Fnaopr.hatenablog.com%2Fentry%2F2024%2F09%2F22%2F093117"
  },
  {
    "rank": 2,
    "title": "Mac やめて Linux PC を自作した - IT戦記",
    "url": "https://amachang.hatenablog.com/entry/2024/09/18/054346",
    "hatena_url": "https://b.hatena.ne.jp/entry?url=https%3A%2F%2Famachang.hatenablog.com%2Fentry%2F2024%2F09%2F18%2F054346"
  },
  {
    "rank": 3,
    "title": "人と話すとMP削れていく人のための、「人付き合い」ルール。 | Books&Apps",
    "url": "https://blog.tinect.jp/?p=87637",
    "hatena_url": "https://b.hatena.ne.jp/entry?url=https%3A%2F%2Fblog.tinect.jp%2F%3Fp%3D87637"
  },
  {
    "rank": 4,
    "title": "大谷翔平 ドジャース 大リーグ史上初「50-50」達成 51本塁打 51盗塁まで記録伸ばす 日本選手最多打点も | NHK | #大谷翔平",
    "url": "https://www3.nhk.or.jp/news/html/20240920/k10014586691000.html",
    "hatena_url": "https://b.hatena.ne.jp/entry?url=https%3A%2F%2Fwww3.nhk.or.jp%2Fnews%2Fhtml%2F20240920%2Fk10014586691000.html"
  },
  {
    "rank": 5,
    "title": "中国がわりとやばい件について③",
    "url": "https://anond.hatelabo.jp/20240919010003",
    "hatena_url": "https://b.hatena.ne.jp/entry?url=https%3A%2F%2Fanond.hatelabo.jp%2F20240919010003"
  },
  {
    "rank": 6,
    "title": "任天堂株式会社 ニュースリリース :2024年9月19日 -株式会社ポケットペアに対する特許権侵害訴訟の提起について｜任天堂",
    "url": "https://www.nintendo.co.jp/corporate/release/2024/240919.html",
    "hatena_url": "https://b.hatena.ne.jp/entry?url=https%3A%2F%2Fwww.nintendo.co.jp%2Fcorporate%2Frelease%2F2024%2F240919.html"
  },
  {
    "rank": 7,
    "title": "科学的根拠に基づく「健康に良い食事」について｜国立健康・栄養研究所",
    "url": "https://www.nibiohn.go.jp/eiken/healthydiet/index.html",
    "hatena_url": "https://b.hatena.ne.jp/entry?url=https%3A%2F%2Fwww.nibiohn.go.jp%2Feiken%2Fhealthydiet%2Findex.html"
  },
  {
    "rank": 8,
    "title": "コイン電池、交換不要に 業界初の自立給電型開発 CR2032代替 SMK | 電波新聞デジタル",
    "url": "https://dempa-digital.com/article/591148",
    "hatena_url": "https://b.hatena.ne.jp/entry?url=https%3A%2F%2Fdempa-digital.com%2Farticle%2F591148"
  },
  {
    "rank": 9,
    "title": "1冊の単語帳を1127日かけて2周したら語彙力が1万2千語になった: わたしが知らないスゴ本は、きっとあなたが読んでいる",
    "url": "https://dain.cocolog-nifty.com/myblog/2024/09/post-785dff.html",
    "hatena_url": "https://b.hatena.ne.jp/entry?url=https%3A%2F%2Fdain.cocolog-nifty.com%2Fmyblog%2F2024%2F09%2Fpost-785dff.html"
  },
  {
    "rank": 10,
    "title": "彼女が妊娠した",
    "url": "https://anond.hatelabo.jp/20240917144927",
    "hatena_url": "https://b.hatena.ne.jp/entry?url=https%3A%2F%2Fanond.hatelabo.jp%2F20240917144927"
  },
  {
    "rank": 11,
    "title": "安倍晋三氏と旧統一教会会長、自民党本部で選挙支援確認か 写真入手：朝日新聞デジタル",
    "url": "https://www.asahi.com/articles/ASS9J2PWQS9JUTIL006M.html",
    "hatena_url": "https://b.hatena.ne.jp/entry?url=https%3A%2F%2Fwww.asahi.com%2Farticles%2FASS9J2PWQS9JUTIL006M.html"
  },
  {
    "rank": 12,
    "title": "「怖い」「背筋凍った」総裁選９人が全員沈黙「ｎｅｗｓ２３」旧統一教会の再調査は？→全員挙手せず不気味スルー「しーん」「失笑」「ダメだこりゃ！」/芸能/デイリースポーツ online",
    "url": "https://www.daily.co.jp/gossip/2024/09/18/0018133897.shtml",
    "hatena_url": "https://b.hatena.ne.jp/entry?url=https%3A%2F%2Fwww.daily.co.jp%2Fgossip%2F2024%2F09%2F18%2F0018133897.shtml"
  },
  {
    "rank": 13,
    "title": "任天堂の胸先三寸で「許されるゲーム」「許されないゲーム」が出てくるのはゲーム業界にとって極めて不健全だと思う - Togetter [トゥギャッター]",
    "url": "https://togetter.com/li/2437158",
    "hatena_url": "https://b.hatena.ne.jp/entry?url=https%3A%2F%2Ftogetter.com%2Fli%2F2437158"
  },
  {
    "rank": 14,
    "title": "学生時代に恋愛を経験しておかないと何故詰むのか",
    "url": "https://anond.hatelabo.jp/20240918111123",
    "hatena_url": "https://b.hatena.ne.jp/entry?url=https%3A%2F%2Fanond.hatelabo.jp%2F20240918111123"
  },
  {
    "rank": 15,
    "title": "京都府立大学、『日本料理大全』のデジタル版を一般公開 | カレントアウェアネス・ポータル",
    "url": "https://current.ndl.go.jp/car/225663",
    "hatena_url": "https://b.hatena.ne.jp/entry?url=https%3A%2F%2Fcurrent.ndl.go.jp%2Fcar%2F225663"
  },
  {
    "rank": 16,
    "title": "実父に14歳から性虐待され5児を産まされた娘を弁護士はどう救ったか…朝ドラ最後の山場｢尊属殺人事件｣の真相 実際の担当弁護士に取材したライターが見た｢虎に翼｣ | PRESIDENT Online（プレジデントオンライン）",
    "url": "https://president.jp/articles/-/86168",
    "hatena_url": "https://b.hatena.ne.jp/entry?url=https%3A%2F%2Fpresident.jp%2Farticles%2F-%2F86168"
  },
  {
    "rank": 17,
    "title": "ASCII.jp：「計算機アプリ作って」→AI「あいよ」 20万個以上のアプリが開発される",
    "url": "https://ascii.jp/elem/000/004/222/4222589/",
    "hatena_url": "https://b.hatena.ne.jp/entry?url=https%3A%2F%2Fascii.jp%2Felem%2F000%2F004%2F222%2F4222589%2F"
  },
  {
    "rank": 18,
    "title": "障害年金について知っておいた方が良い話",
    "url": "https://anond.hatelabo.jp/20240920134759",
    "hatena_url": "https://b.hatena.ne.jp/entry?url=https%3A%2F%2Fanond.hatelabo.jp%2F20240920134759"
  },
  {
    "rank": 19,
    "title": "勉強から研究へ",
    "url": "https://member.ipmu.jp/yuji.tachikawa/misc/from-benkyo-to-kenkyu.html",
    "hatena_url": "https://b.hatena.ne.jp/entry?url=https%3A%2F%2Fmember.ipmu.jp%2Fyuji.tachikawa%2Fmisc%2Ffrom-benkyo-to-kenkyu.html"
  },
  {
    "rank": 20,
    "title": "【速報】イスラエルがダミー会社でポケベル製造か|47NEWS（よんななニュース）",
    "url": "https://www.47news.jp/11507532.html",
    "hatena_url": "https://b.hatena.ne.jp/entry?url=https%3A%2F%2Fwww.47news.jp%2F11507532.html"
  },
  {
    "rank": 21,
    "title": "PyCon JPの技術に対する不正の告発、並びに技術者と大衆に対しての警鐘 #Python - Qiita",
    "url": "https://qiita.com/python_bokume2/items/7aa80b73010919007581",
    "hatena_url": "https://b.hatena.ne.jp/entry?url=https%3A%2F%2Fqiita.com%2Fpython_bokume2%2Fitems%2F7aa80b73010919007581"
  },
  {
    "rank": 22,
    "title": "パソコンの画面全体に偽のメッセージが表示され操作不能になる手口が増加中 | 情報セキュリティ | IPA 独立行政法人 情報処理推進機構",
    "url": "https://www.ipa.go.jp/security/anshin/attention/2024/mgdayori20240917.html",
    "hatena_url": "https://b.hatena.ne.jp/entry?url=https%3A%2F%2Fwww.ipa.go.jp%2Fsecurity%2Fanshin%2Fattention%2F2024%2Fmgdayori20240917.html"
  },
  {
    "rank": 23,
    "title": "社内ヘルプデスクのチケット管理システム、みんな何使ってるんですか？→有益すぎる情報が集まる - Togetter [トゥギャッター]",
    "url": "https://togetter.com/li/2437308",
    "hatena_url": "https://b.hatena.ne.jp/entry?url=https%3A%2F%2Ftogetter.com%2Fli%2F2437308"
  },
  {
    "rank": 24,
    "title": "8kg痩せた私がここんところずっと食ってるメニュー",
    "url": "https://anond.hatelabo.jp/20240917232023",
    "hatena_url": "https://b.hatena.ne.jp/entry?url=https%3A%2F%2Fanond.hatelabo.jp%2F20240917232023"
  },
  {
    "rank": 25,
    "title": "自分も中国とはかれこれ20年くらいビジネスをしていて、長いこと中国にも住..",
    "url": "https://anond.hatelabo.jp/20240920104856",
    "hatena_url": "https://b.hatena.ne.jp/entry?url=https%3A%2F%2Fanond.hatelabo.jp%2F20240920104856"
  },
  {
    "rank": 26,
    "title": "画像・写真：東大・一橋大を地方移転：時事ドットコム",
    "url": "https://www.jiji.com/jc/p?id=20240920172959-0081842606",
    "hatena_url": "https://b.hatena.ne.jp/entry?url=https%3A%2F%2Fwww.jiji.com%2Fjc%2Fp%3Fid%3D20240920172959-0081842606"
  },
  {
    "rank": 27,
    "title": "news16 | 株式会社ポケットペア",
    "url": "https://www.pocketpair.jp/news/news16?lang=ja",
    "hatena_url": "https://b.hatena.ne.jp/entry?url=https%3A%2F%2Fwww.pocketpair.jp%2Fnews%2Fnews16%3Flang%3Dja"
  },
  {
    "rank": 28,
    "title": "横着甘やかされカマキリの半生",
    "url": "https://anond.hatelabo.jp/20240918193847",
    "hatena_url": "https://b.hatena.ne.jp/entry?url=https%3A%2F%2Fanond.hatelabo.jp%2F20240918193847"
  },
  {
    "rank": 29,
    "title": "ジョセフ・ヒース「反自由主義的リベラリズム」（2024年7月30日） – 経済学101",
    "url": "https://econ101.jp/illiberal-liberalism/",
    "hatena_url": "https://b.hatena.ne.jp/entry?url=https%3A%2F%2Fecon101.jp%2Filliberal-liberalism%2F"
  },
  {
    "rank": 30,
    "title": "任天堂が対パルワールド訴訟で使用した特許はたぶんこれ（栗原潔） - エキスパート - Yahoo!ニュース",
    "url": "https://news.yahoo.co.jp/expert/articles/59f880c5e13b9292f0e3ab2d1d55ce8bdbfdb97f",
    "hatena_url": "https://b.hatena.ne.jp/entry?url=https%3A%2F%2Fnews.yahoo.co.jp%2Fexpert%2Farticles%2F59f880c5e13b9292f0e3ab2d1d55ce8bdbfdb97f"
  }
]